sre_snapshots/__init__.py
sre_snapshots/download_snapshots.py
sre_snapshots/upload_snapshots.py
sre_snapshots/utils.py
sre_snapshots-0.0.8.dist-info/LICENSE
sre_snapshots-0.0.8.dist-info/METADATA
sre_snapshots-0.0.8.dist-info/WHEEL
sre_snapshots-0.0.8.dist-info/top_level.txt
sre_snapshots-0.0.8.dist-info/RECORD
