Metadata-Version: 2.1
Name: sre-snapshots
Version: 0.0.8
Summary: Download SERP snapshots from the MongoDB library
Home-page: UNKNOWN
Author: James Wolman
Author-email: James.Wolman@found.co.uk
License: MIT
Platform: UNKNOWN
Classifier: Programming Language :: Python :: 3
Classifier: License :: OSI Approved :: MIT License
Classifier: Operating System :: OS Independent
Classifier: Development Status :: 4 - Beta
Classifier: Intended Audience :: Developers
Classifier: Natural Language :: English
Classifier: Programming Language :: Python :: 3.7
Classifier: Programming Language :: Python :: 3.8
License-File: LICENSE
Requires-Dist: requests (==2.25.1)
Requires-Dist: pymongo (==3.10.1)
